LICENSE
README.md
setup.py
HawkScan.egg-info/PKG-INFO
HawkScan.egg-info/SOURCES.txt
HawkScan.egg-info/dependency_links.txt
HawkScan.egg-info/requires.txt
HawkScan.egg-info/top_level.txt
modules/__init__.py
modules/auto_update.py
modules/banner.py
modules/before_run.py
modules/bypass_forbidden.py
modules/bypass_waf.py
modules/check_cms.py
modules/check_socketio.py
modules/check_subdomain.py
modules/detect_waf.py
modules/google_dorks.py
modules/manage_dir.py
modules/output.py
modules/parsing_html.py
modules/resume.py
modules/send_notify.py
modules/terminal_size.py
report/__init__.py
report/creat_report.py