Metadata-Version: 2.1
Name: HawkScan
Version: 2.2
Summary: Security Tool for Reconnaissance and Information Gathering on a website. (python 3.x)
Home-page: https://github.com/c0dejump/HawkScan/
Author: c0dejump
Author-email: codejumpgame@gmail.com
License: UNKNOWN
Project-URL: Bug Tracker, https://github.com/c0dejump/HawkScan/issues
Platform: UNKNOWN
Classifier: Programming Language :: Python :: 3
Classifier: License :: OSI Approved :: MIT License
Classifier: Operating System :: OS Independent
License-File: LICENSE
